jupyter_forward/__init__.py
jupyter_forward/_version.py
jupyter_forward/cli.py
jupyter_forward/console.py
jupyter_forward/core.py
jupyter_forward/helpers.py
jupyter_forward/py.typed
jupyter_forward-2025.1.16.dist-info/LICENSE
jupyter_forward-2025.1.16.dist-info/METADATA
jupyter_forward-2025.1.16.dist-info/WHEEL
jupyter_forward-2025.1.16.dist-info/entry_points.txt
jupyter_forward-2025.1.16.dist-info/top_level.txt
jupyter_forward-2025.1.16.dist-info/RECORD
