Metadata-Version: 2.2
Name: jupyter-forward
Version: 2025.1.16
Summary: Jupyter Lab Port Forwarding Utility
Maintainer-email: Xdev <xdev@ucar.edu>
License: Apache Software License 2.0
Project-URL: Documentation, https://github.com/ncar-xdev/jupyter-forward
Project-URL: Homepage, https://github.com/ncar-xdev/jupyter-forward
Project-URL: Source, https://github.com/ncar-xdev/jupyter-forward
Project-URL: Tracker, https://github.com/ncar-xdev/jupyter-forward/issues
Keywords: jupyter-forward
Classifier: Development Status :: 2 - Pre-Alpha
Classifier: Intended Audience :: Science/Research
Classifier: License :: OSI Approved :: Apache Software License
Classifier: Natural Language :: English
Classifier: Operating System :: OS Independent
Classifier: Programming Language :: Python :: 3
Classifier: Programming Language :: Python :: 3.10
Classifier: Programming Language :: Python :: 3.11
Classifier: Programming Language :: Python :: 3.12
Classifier: Topic :: Scientific/Engineering
Requires-Python: >=3.10
License-File: LICENSE
Requires-Dist: typer>=0.9
Requires-Dist: fabric>=2.5
Requires-Dist: rich>=13.0.0
